{
    "users": {
        "-MtmtYJtvU5BSjWDbErP": {
            "id": "3963355c-2daf-45ff-9578-8966b35e9093",
            "fullName": "Quintin",
            "avatar": "https://robohash.org/etauttempora.png?size=500x500&set=set1"
        },
        "-MtmtYJuFlhaSXVzU4yd": {
            "id": "f587e316-3d59-4bcb-8aa0-d511e6e03394",
            "fullName": "Ham",
            "avatar": "https://robohash.org/rerumquassint.png?size=500x500&set=set1"
        },
        "-MtmtYJwn-QuYjJSdbN2": {
            "id": "77f4de09-0c5f-4437-8abd-e063175ddfcf",
            "fullName": "Hadrian",
            "avatar": "https://robohash.org/facilislaborumlaboriosam.png?size=500x500&set=set1"
        },
        "-MtmtYJxaJheJ3WNdv8s": {
            "id": "4919d003-b94b-4169-9a1e-450bbe192087",
            "fullName": "Bendite",
            "avatar": "https://robohash.org/utetincidunt.png?size=500x500&set=set1"
        },
        "-MtmtYJzgQ-oWFwzOTOw": {
            "id": "2b3bad0a-9a2e-4f88-ad58-6469eec2686c",
            "fullName": "Jackelyn",
            "avatar": "https://robohash.org/quisdolorescorrupti.png?size=500x500&set=set1"
        },
        "-MtmtYK09fi-B0vHELUn": {
            "id": "a49bf7f2-2c15-4445-a6e1-75f149ec1999",
            "fullName": "Maurits",
            "avatar": "https://robohash.org/dolordebitisnisi.png?size=500x500&set=set1"
        },
        "-MtmtYK1vtmYmTm-FAYt": {
            "id": "df243da5-d3df-43fb-ae07-e62fedba6600",
            "fullName": "Augustin",
            "avatar": "https://robohash.org/molestiaedignissimosconsectetur.png?size=500x500&set=set1"
        },
        "-MtmtYK340nXpoTj2JBk": {
            "id": "45c9bd79-af03-412f-9289-43cf15a6f69e",
            "fullName": "Wright",
            "avatar": "https://robohash.org/molestiaenemomollitia.png?size=500x500&set=set1"
        },
        "-MtmtYK4_Mp-HUag1oK0": {
            "id": "9fb57565-44c7-4f3e-8d79-ce2f982bd899",
            "fullName": "Berget",
            "avatar": "https://robohash.org/mollitiaplaceataut.png?size=500x500&set=set1"
        },
        "-MtmtYK6xf5Z0u_5fr1K": {
            "id": "b2f84a69-1416-41ef-87dc-a80ae80130ee",
            "fullName": "Selinda",
            "avatar": "https://robohash.org/illumutid.png?size=500x500&set=set1"
        }
    }
}